paralelocs_beam/__init__.py
paralelocs_beam/__main__.py
paralelocs_beam/cli.py
paralelocs_beam/io/__init__.py
paralelocs_beam/io/dbconnection.py
paralelocs_beam/io/relationaldatabaseio.py
paralelocs_beam/transform/__init__.py
paralelocs_beam/transform/bigquery.py
paralelocs_beam/transform/join.py
paralelocs_beam/utils/__init__.py
paralelocs_beam/utils/bigquery.py
paralelocs_beam-1.0.4.dist-info/AUTHORS.rst
paralelocs_beam-1.0.4.dist-info/LICENSE
paralelocs_beam-1.0.4.dist-info/METADATA
paralelocs_beam-1.0.4.dist-info/WHEEL
paralelocs_beam-1.0.4.dist-info/top_level.txt
paralelocs_beam-1.0.4.dist-info/RECORD
