Metadata-Version: 2.1
Name: paralelocs-beam
Version: 1.0.4
Summary: Paraleo CS Custom packages to work with Apache Beam on Python SDK
Home-page: https://gitlab.com/lucasmagalhaes/paralelocs_beam
Author: Paralelo Consultoria e Servicos Ltda
Author-email: contato@paralelocs.com.br
License: Apache-2.0
Project-URL: Changelog, https://gitlab.com/lucasmagalhaes/paralelocs_beam/blob/master/CHANGELOG.rst
Project-URL: Issue Tracker, https://gitlab.com/lucasmagalhaes/paralelocs_beam/issues
Platform: UNKNOWN
Classifier: Development Status :: 5 - Production/Stable
Classifier: Intended Audience :: Developers
Classifier: License :: OSI Approved :: Apache Software License
Classifier: Operating System :: Unix
Classifier: Operating System :: POSIX
Classifier: Operating System :: Microsoft :: Windows
Classifier: Programming Language :: Python
Classifier: Programming Language :: Python :: 3
Classifier: Programming Language :: Python :: 3.5
Classifier: Programming Language :: Python :: 3.6
Classifier: Programming Language :: Python :: 3.7
Classifier: Programming Language :: Python :: 3.8
Classifier: Programming Language :: Python :: Implementation :: CPython
Classifier: Programming Language :: Python :: Implementation :: PyPy
Classifier: Topic :: Utilities
Requires-Python: >=3.0.*, !=3.1.*, !=3.2.*, !=3.3.*, !=3.4.*
Requires-Dist: SQLAlchemy (>=1.3.8)
Requires-Dist: psycopg2-binary (>=2.8.3)
